Metadata-Version: 2.1
Name: odoo-addon-sale-coupon-financial-risk
Version: 15.0.1.0.1
Summary: Compatibilize coupons with sale financial risk
Home-page: https://github.com/OCA/sale-promotion
Author: Tecnativa, Odoo Community Association (OCA)
Author-email: support@odoo-community.org
License: AGPL-3
Platform: UNKNOWN
Classifier: Programming Language :: Python
Classifier: Framework :: Odoo
Classifier: Framework :: Odoo :: 15.0
Classifier: License :: OSI Approved :: GNU Affero General Public License v3
Requires-Python: >=3.8
Requires-Dist: odoo-addon-sale-financial-risk <15.1dev,>=15.0dev
Requires-Dist: odoo <15.1dev,>=15.0a
